dash_auth/__init__.py
dash_auth/auth.py
dash_auth/basic_auth.py
dash_auth/public_routes.py
dash_auth/version.py
dash_auth-2.2.1.dist-info/METADATA
dash_auth-2.2.1.dist-info/WHEEL
dash_auth-2.2.1.dist-info/top_level.txt
dash_auth-2.2.1.dist-info/RECORD
